material/404.html
material/__init__.py
material/base.html
material/main.html
material/mkdocs_theme.yml
material/assets/images/favicon.png
material/assets/images/logo.png
material/assets/images/icons/bitbucket.4ebea66e.svg
material/assets/images/icons/github.a4034fb1.svg
material/assets/images/icons/gitlab.348cdb3a.svg
material/assets/javascripts/application.cb37bb38.js
material/assets/javascripts/modernizr.0b5df86e.js
material/assets/javascripts/lunr/lunr.da.js
material/assets/javascripts/lunr/lunr.de.js
material/assets/javascripts/lunr/lunr.du.js
material/assets/javascripts/lunr/lunr.es.js
material/assets/javascripts/lunr/lunr.fi.js
material/assets/javascripts/lunr/lunr.fr.js
material/assets/javascripts/lunr/lunr.hu.js
material/assets/javascripts/lunr/lunr.it.js
material/assets/javascripts/lunr/lunr.jp.js
material/assets/javascripts/lunr/lunr.multi.js
material/assets/javascripts/lunr/lunr.no.js
material/assets/javascripts/lunr/lunr.pt.js
material/assets/javascripts/lunr/lunr.ro.js
material/assets/javascripts/lunr/lunr.ru.js
material/assets/javascripts/lunr/lunr.stemmer.support.js
material/assets/javascripts/lunr/lunr.sv.js
material/assets/javascripts/lunr/lunr.tr.js
material/assets/javascripts/lunr/tinyseg.js
material/assets/stylesheets/application-palette.6079476c.css
material/assets/stylesheets/application.b80b25f7.css
material/partials/footer.html
material/partials/header.html
material/partials/hero.html
material/partials/language.html
material/partials/nav-item.html
material/partials/nav.html
material/partials/search.html
material/partials/social.html
material/partials/source.html
material/partials/tabs-item.html
material/partials/tabs.html
material/partials/toc-item.html
material/partials/toc.html
material/partials/integrations/analytics.html
material/partials/integrations/disqus.html
material/partials/language/ar.html
material/partials/language/ca.html
material/partials/language/da.html
material/partials/language/de.html
material/partials/language/en.html
mkdocs_ponylang-0.2.8.dist-info/LICENSE
mkdocs_ponylang-0.2.8.dist-info/METADATA
mkdocs_ponylang-0.2.8.dist-info/WHEEL
mkdocs_ponylang-0.2.8.dist-info/entry_points.txt
mkdocs_ponylang-0.2.8.dist-info/top_level.txt
mkdocs_ponylang-0.2.8.dist-info/RECORD
