Metadata-Version: 2.1
Name: mkdocs-ponylang
Version: 0.2.8
Summary: Ponylang Material theme for MkDocs
Home-page: https://github.com/ponylang/mkdocs-theme
Author: The Pony Developers
License: MIT
Keywords: mkdocs,documentation,theme,ponylang
Platform: UNKNOWN
Requires-Dist: mkdocs (>=1.0.4)
Requires-Dist: Pygments (>=2.2)
Requires-Dist: pymdown-extensions (>=3.4)
Requires-Dist: setuptools (>=38.6.0)
